syspath_hack/__init__.py
syspath_hack/pure.py
syspath_hack-0.4.0.dist-info/licenses/LICENSE
syspath_hack-0.4.0.dist-info/METADATA
syspath_hack-0.4.0.dist-info/WHEEL
syspath_hack-0.4.0.dist-info/top_level.txt
syspath_hack-0.4.0.dist-info/RECORD
