Metadata-Version: 2.4
Name: syspath-hack
Version: 0.4.0
Summary: Utilities for locating project roots and keeping sys.path tidy
Author-email: Payton McIntosh <pmcintosh@df12.net>
License: ISC
Project-URL: Homepage, https://df12.studio/docs.html
Project-URL: Repository, https://github.com/leynos/syspath-hack
Requires-Python: >=3.10
License-File: LICENSE
Dynamic: license-file
